{
  "caseId": "SIGS-V2-053",
  "expectedDecision": "DO_NOT_CONTINUE",
  "expectedLabel": "Nu continua",
  "groundTruthIsScam": true,
  "primaryUrlExpected": "https://fancourier-livrare-28.test/awb?id=SMY883201004",
  "signalsExpected": [
    "COURIER_BRAND_CONTEXT",
    "DELIVERY_SMALL_FEE_REQUEST",
    "OFFICIAL_DOMAIN_MISMATCH",
    "CARD_DATA_REQUEST",
    "URGENCY_LANGUAGE"
  ],
  "sourceStatesExpected": {
    "web_risk": "SIGS-V2-053_web_risk.json",
    "urlscan": "SIGS-V2-053_urlscan.json",
    "virustotal": "SIGS-V2-053_virustotal.json"
  },
  "notes": "Contextul real de așteptare colet nu reduce riscul."
}