{
  "caseId": "SIGS-V2-051",
  "provider": "URLSCAN",
  "inputUrl": "https://dpd-livrare-26.test/locker?id=DPDRO7451102",
  "status": "SUCCESS",
  "mockVariant": "urlscan_malicious",
  "finalUrl": "https://dpd-livrare-26.test/locker?id=DPDRO7451102",
  "verdict": "malicious",
  "screenshotAvailable": true,
  "forms": [
    "apk_download"
  ],
  "redirectChain": [],
  "server": {
    "country": "VN",
    "asn": "TEST-BAD-AS"
  },
  "certificate": {
    "valid": true,
    "issuer": "ZeroSSL/R3 test",
    "ageDays": 3
  }
}